zenyxvm/__init__.py
zenyxvm/__main__.py
zenyxvm-1.1.3.dist-info/METADATA
zenyxvm-1.1.3.dist-info/WHEEL
zenyxvm-1.1.3.dist-info/licenses/LICENSE
zenyxvm-1.1.3.dist-info/RECORD
